tranzit/__init__.py
tranzit/cli.py
tranzit/starter/__init__.py
tranzit/starter/main.py
tranzit/starter/server.yml
tranzit/starter/apps/__init__.py
tranzit/starter/apps/hello/__init__.py
tranzit/starter/apps/hello/app.yml
tranzit/starter/apps/hello/routes.py
tranzit/starter/apps/hello/views.py
tranzit/starter/apps/hello/static/camel.html
tranzit/starter/apps/hello/static/camel.jpg
tranzit/starter/common/static/tz.js
tranzit/web/__init__.py
tranzit/web/server.py
tranzit/web/ws_server.py
tranzit-0.1.dist-info/DESCRIPTION.rst
tranzit-0.1.dist-info/METADATA
tranzit-0.1.dist-info/RECORD
tranzit-0.1.dist-info/WHEEL
tranzit-0.1.dist-info/entry_points.txt
tranzit-0.1.dist-info/metadata.json
tranzit-0.1.dist-info/top_level.txt
