Metadata-Version: 1.1
Name: tranzit
Version: 0.1
Summary: asynchronous http web framework based on aiohttp providing websocket server functionality
Home-page: https://github.com/artkra/tranzit
Author: Art Krasnyy
Author-email: artkrasnyy@gmail.com
License: GPL-2.0
Download-URL: https://github.com/artkra/tranzit/archive/0.1.tar.gz
Keywords: async http web framework websocket server
Platform: UNKNOWN
